xmlriver/__init__.py
xmlriver/exceptions.py
xmlriver/google.py
xmlriver/xmlriver.py
xmlriver/yandex.py
xmlriver-0.14.dist-info/LICENSE
xmlriver-0.14.dist-info/METADATA
xmlriver-0.14.dist-info/WHEEL
xmlriver-0.14.dist-info/top_level.txt
xmlriver-0.14.dist-info/RECORD
