Metadata-Version: 2.1
Name: xmlriver
Version: 0.14
Summary: Пакет для работы с поисковой выдачей Google и Yandex по API через сервис XMLRiver / Package for working with Google and Yandex search results via API via XMLRiver service.
Home-page: https://github.com/KursHub-ru/xmlriver
Author: Ivan Sharkov
Author-email: admin@kurshub.ru
Project-URL: Documentation, https://github.com/KursHub-ru/xmlriver
Project-URL: GitHub, https://github.com/KursHub-ru/xmlriver
Project-URL: Homepage, https://0pl.ru
Project-URL: Organization, https://kurshub.ru
Project-URL: Telegram, https://t.me/sharkovseo
Keywords: google,yandex,xmlriver,xmlriver.com
Classifier: Programming Language :: Python :: 3
Classifier: License :: OSI Approved :: GNU General Public License (GPL)
Classifier: Operating System :: OS Independent
Requires-Python: >=3.7
License-File: LICENSE
Requires-Dist: requests (>=2.25)
Requires-Dist: xmltodict (>=0.12)
